hudsucker/__init__.py
hudsucker/__main__.py
hudsucker/_version.py
hudsucker/industries.py
hudsucker/proxy.py
hudsucker-0.2.1.dist-info/DESCRIPTION.rst
hudsucker-0.2.1.dist-info/METADATA
hudsucker-0.2.1.dist-info/RECORD
hudsucker-0.2.1.dist-info/WHEEL
hudsucker-0.2.1.dist-info/entry_points.txt
hudsucker-0.2.1.dist-info/metadata.json
hudsucker-0.2.1.dist-info/top_level.txt
hudsucker-0.2.1.dist-info/zip-safe
