Metadata-Version: 2.0
Name: hudsucker
Version: 0.2.1
Summary: Hudsucker Proxy Generator
Home-page: https://github.com/RobRuana/hudsucker
Author: Rob Ruana
Author-email: rob@robruana.com
License: MIT
Download-URL: http://pypi.python.org/pypi/hudsucker
Platform: any
Classifier: Development Status :: 4 - Beta
Classifier: Environment :: Console
Classifier: Intended Audience :: End Users/Desktop
Classifier: License :: OSI Approved :: MIT License
Classifier: Operating System :: OS Independent
Classifier: Programming Language :: Python
Classifier: Programming Language :: Python :: 2
Classifier: Programming Language :: Python :: 3
Classifier: Topic :: Utilities
Requires-Dist: Pillow (>=3.3.1)
Requires-Dist: cssselect (>=0.9.2)
Requires-Dist: lxml (>=3.6.1)
Requires-Dist: requests (>=2.10.0)
Requires-Dist: six
